.gitignore
Example.ipynb
LICENSE
MANIFEST.in
README.md
pyproject.toml
schema.png
schema_exofile.png
setup.cfg
setup.py
exofile/__init__.py
exofile/archive.py
exofile/config.py
exofile/default_param.yaml
exofile/exceptions.py
exofile/param.yaml
exofile/table_custom.py
exofile/utils.py
exofile.egg-info/PKG-INFO
exofile.egg-info/SOURCES.txt
exofile.egg-info/dependency_links.txt
exofile.egg-info/not-zip-safe
exofile.egg-info/requires.txt
exofile.egg-info/top_level.txt
extras/generate_test_data.py
extras/migrate_google_sheet.py
extras/migrate_tables.py
extras/update_file.py
tests/data/single_param.csv
tests/data/two_params.csv