Metadata-Version: 2.1
Name: exofile
Version: 0.2.1
Summary: A complete exoplanet archive table.
Home-page: https://github.com/AntoineDarveau/exofile
Author: Antoine Darveau-Bernier
Author-email: antoine.darveau@gmail.com
License: MIT License
Platform: UNKNOWN
Provides-Extra: dev
License-File: LICENSE
